jsonpath_kv/GetJsonValue.py
jsonpath_kv/__init__.py
jsonpath_kv-0.0.7.dist-info/LICENSE
jsonpath_kv-0.0.7.dist-info/METADATA
jsonpath_kv-0.0.7.dist-info/WHEEL
jsonpath_kv-0.0.7.dist-info/top_level.txt
jsonpath_kv-0.0.7.dist-info/RECORD
