Metadata-Version: 2.1
Name: jsonpath-kv
Version: 0.0.7
Summary: Gets the value in the JSON data
Home-page: https://github.com/WangHaoz/GetJsonValue
Author: Wanghao
Author-email: 947001731@qq.com
License: UNKNOWN
Platform: UNKNOWN
Classifier: Programming Language :: Python :: 3
Classifier: License :: OSI Approved :: Apache Software License
Classifier: Operating System :: OS Independent
